MANIFEST.in
ncrypt.c
ncrypt_bignum.pyx
ncrypt_cipher.pyx
ncrypt_dh.pyx
ncrypt_digest.pyx
ncrypt_err.pyx
ncrypt_rand.pyx
ncrypt_rsa.pyx
ncrypt_ssl.pyx
ncrypt_x509.pyx
setup.py
utils.c
include/ncrypt_dh.pxd
include/ncrypt_digest.pxd
include/ncrypt_rsa.pxd
include/ncrypt_x509.pxd
include/utils.h
ncrypt/__init__.py
ncrypt/bignum.py
ncrypt/cipher.py
ncrypt/dh.py
ncrypt/digest.py
ncrypt/err.py
ncrypt/rand.py
ncrypt/rsa.py
ncrypt/ssl.py
ncrypt/x509.py
ncrypt.egg-info/PKG-INFO
ncrypt.egg-info/SOURCES.txt
ncrypt.egg-info/dependency_links.txt
ncrypt.egg-info/requires.txt
ncrypt.egg-info/top_level.txt
ncrypt/test/__init__.py
ncrypt/test/decrypt.py
ncrypt/test/encrypt.py
ncrypt/test/filterprog.py
ncrypt/test/hash.py
ncrypt/test/md5hash.py
ncrypt/test/sha1hash.py
ncrypt/test/test.py
ncrypt/test/testcipher.py
ncrypt/test/testdigest.py
ncrypt/test/testrand.py
ncrypt/test/testrsa.py
ncrypt/test/ssl/__init__.py
ncrypt/test/ssl/sslclient.py
ncrypt/test/ssl/sslserver.py
ncrypt/test/ssl/sslserver1.py