Metadata-Version: 1.0
Name: ncrypt
Version: 0.6.4
Summary: Yet another OpenSSL wrapper for python
Home-page: http://www.tachyontech.net
Author: K.S Sreeram, Jeethu Rao
Author-email: sreeram@tachyontech.net, jeethu@tachyontech.net
License: UNKNOWN
Platform: UNKNOWN
Classifier: Development Status :: 3 - Alpha
Classifier: Intended Audience :: Developers
Classifier: License :: OSI Approved :: GNU General Public License (GPL)
Classifier: Programming Language :: Python
Classifier: Programming Language :: C
Classifier: Topic :: Software Development :: Libraries :: Python Modules
Classifier: Topic :: Security :: Cryptography
Classifier: Operating System :: Microsoft :: Windows
